README.rst
setup.py
xstatic_release/__init__.py
xstatic_release.egg-info/PKG-INFO
xstatic_release.egg-info/SOURCES.txt
xstatic_release.egg-info/dependency_links.txt
xstatic_release.egg-info/entry_points.txt
xstatic_release.egg-info/top_level.txt