Metadata-Version: 1.0
Name: xstatic-release
Version: 1.2.1
Summary: Tool to help OpenStack Horizon developers package xstatic
Home-page: UNKNOWN
Author: UNKNOWN
Author-email: UNKNOWN
License: UNKNOWN
Platform: UNKNOWN
